Workbook

Sheet Inputs
A1: Particulars | B1: Value
A2: Revenue Growth | B2: =AVERAGE(Historicals!C3:F3) -> 0.10277561
A3: EBITDA Margin | B3: =AVERAGE(Historicals!B5:F5) -> 0.20889009
A4: Tax Rate | B4: =AVERAGE(Historicals!B10:F10) -> 0.25662
A5: Capex % of Revenue | B5: =AVERAGE(3.25%,3.64%,4.07%,3.26%,3.92%) -> 0.03628
A6: Change in NWC % of Revenue | B6: =AVERAGE(Historicals!B15:F15) -> 0.0047453057
A7: WACC | B7: =B16*B13+B15*B14*(1-B4) -> 0.09748572
A8: Terminal Growth | B8: 0.05
A9: D&A % of Revenue | B9: =AVERAGE(Historicals!B6/Historicals!B2,Historicals!C6/Historicals!C2,Historicals!D6/Historicals!D2,Historicals!E6/Historicals!E2,Historicals!F6/Historicals!F2) -> 0.025767523
A10: Risk Free Rate | B10: 0.0713
A11: Beta | B11: 0.4
A12: Market Return | B12: 0.1368
A13: Cost of Equity | B13: =B10+B11*(B12-B10) -> 0.0975
A14: Cost of Debt | B14: =54.22/AVERAGE(454.14,417.21) -> 0.12445057
A15: Debt % | B15: =B19/B20 -> 0.0028639936
A16: Equity % | B16: =B18/B20 -> 0.99713601
A18: Market Cap | B18: 145257
A19: Debt | B19: 417.21
A20: Total Capital | B20: =B18+B19 -> 145674.21
A21: Cash & Bank (₹ Cr) | B21: 298.9
A22: Shares Outstanding (Cr) | B22: 101.7766
A24: Note: Monetary values are in ₹ Crore unless otherwise stated.

Sheet Historicals
A1: Particulars | B1: FY2022 | C1: FY2023 | D1: FY2024 | E1: FY2025 | F1: FY2026
A2: Revenue | B2: 9920.96 | C2: 11799.1 | D2: 12382.99 | E2: 13140.31 | F2: 14600.83
A3: Revenue Growth % | C3: =(C2/B2)-1 -> 0.18931031 | D3: =(D2/C2)-1 -> 0.049485978 | E3: =(E2/D2)-1 -> 0.061158089 | F3: =(F2/E2)-1 -> 0.11114806
A4: EBITDA | B4: 1856.41 | C4: 1986.09 | D4: 2708.45 | E4: 3010.58 | F4: 3521.3
A5: EBITDA Margin % | B5: =B4/B2 -> 0.18712 | C5: =C4/C2 -> 0.16832555 | D5: =D4/D2 -> 0.21872343 | E5: =E4/E2 -> 0.22911027 | F5: =F4/F2 -> 0.24117122
A6: Depreciation & Amortisation | B6: 239.61 | C6: 269.74 | D6: 340.66 | E6: 358.48 | F6: 394.71
A7: EBIT | B7: =B4-B6 -> 1616.8 | C7: =C4-C6 -> 1716.35 | D7: =D4-D6 -> 2367.79 | E7: =E4-E6 -> 2652.1 | F7: =F4-F6 -> 3126.59
A8: EBIT Margin % | B8: =B7/B2 -> 0.1629681 | C8: =C7/C2 -> 0.14546448 | D8: =D7/D2 -> 0.19121311 | E8: =E7/E2 -> 0.20182933 | F8: =F7/F2 -> 0.21413783
A9: Tax | B9: 407.02 | C9: 434.37 | D9: 631.93 | E9: 726.53 | F9: 849.45
A10: Tax Rate % | B10: 0.2522 | C10: 0.2521 | D10: 0.2656 | E10: 0.2574 | F10: 0.2558
A11: PAT | B11: 1207.56 | C11: 1273.25 | D11: 1729.38 | E11: 2076.24 | F11: 2448.92
A12: PAT Margin % | B12: =B11/B2 -> 0.12171806 | C12: =C11/C2 -> 0.10791077 | D12: =D11/D2 -> 0.13965771 | E12: =E11/E2 -> 0.1580054 | F12: =F11/F2 -> 0.16772471
A13: Working Capital | B13: 1432.25 | C13: 1402.02 | D13: 955.87 | E13: 823.04 | F13: 797.27
A14: Change in NWC | B14: 736.05 | C14: =C13-B13 -> -30.23 | D14: =D13-C13 -> -446.15 | E14: =E13-D13 -> -132.83 | F14: =F13-E13 -> -25.77
A15: Change in NWC % of Revenue | B15: =B14/B2 -> 0.074191409 | C15: =C14/C2 -> -0.0025620598 | D15: =D14/D2 -> -0.036029263 | E15: =E14/E2 -> -0.01010859 | F15: =F14/F2 -> -0.0017649682
A17: Note: Monetary values are in ₹ Crore; percentages are shown as %.

Sheet Forecast
A1: Particulars | B1: FY2027E | C1: FY2028E | D1: FY2029E | E1: FY2030E | F1: FY2031E
A2: Revenue | B2: =Historicals!F2*(1+B3) -> 16101.439 | C2: =B2*(1+C3) -> 17756.274 | D2: =C2*(1+D3) -> 19581.186 | E2: =D2*(1+E3) -> 21593.655 | F2: =E2*(1+F3) -> 23812.956
A3: Revenue Growth % | B3: =Inputs!$B$2 -> 0.10277561 | C3: =Inputs!$B$2 -> 0.10277561 | D3: =Inputs!$B$2 -> 0.10277561 | E3: =Inputs!$B$2 -> 0.10277561 | F3: =Inputs!$B$2 -> 0.10277561
A4: EBITDA | B4: =B2*B5 -> 3363.4311 | C4: =C2*C5 -> 3709.1098 | D4: =D2*D5 -> 4090.3158 | E4: =E2*E5 -> 4510.7005 | F4: =F2*F5 -> 4974.2905
A5: EBITDA Margin % | B5: =Inputs!$B$3 -> 0.20889009 | C5: =Inputs!$B$3 -> 0.20889009 | D5: =Inputs!$B$3 -> 0.20889009 | E5: =Inputs!$B$3 -> 0.20889009 | F5: =Inputs!$B$3 -> 0.20889009
A6: Depreciation & Amortisation | B6: =B2*Inputs!$B$9 -> 414.8942 | C6: =C2*Inputs!$B$9 -> 457.53521 | D6: =D2*Inputs!$B$9 -> 504.55867 | E6: =E2*Inputs!$B$9 -> 556.41499 | F6: =F2*Inputs!$B$9 -> 613.60088
A7: EBIT | B7: =B4-B6 -> 2948.5369 | C7: =C4-C6 -> 3251.5746 | D7: =D4-D6 -> 3585.7572 | E7: =E4-E6 -> 3954.2856 | F7: =F4-F6 -> 4360.6897
A8: Tax Rate % | B8: =Inputs!$B$4 -> 0.25662 | C8: =Inputs!$B$4 -> 0.25662 | D8: =Inputs!$B$4 -> 0.25662 | E8: =Inputs!$B$4 -> 0.25662 | F8: =Inputs!$B$4 -> 0.25662
A9: Tax | B9: =B7*B8 -> 756.65355 | C9: =C7*C8 -> 834.41908 | D9: =D7*D8 -> 920.17701 | E9: =E7*E8 -> 1014.7488 | F9: =F7*F8 -> 1119.0402
A10: EBIT (1-Tax) | B10: =B7*(1-B8) -> 2191.8834 | C10: =C7*(1-C8) -> 2417.1555 | D10: =D7*(1-D8) -> 2665.5802 | E10: =E7*(1-E8) -> 2939.5368 | F10: =F7*(1-F8) -> 3241.6495
A11: Capex | B11: =B2*Inputs!$B$5 -> 584.16021 | C11: =C2*Inputs!$B$5 -> 644.19764 | D11: =D2*Inputs!$B$5 -> 710.40544 | E11: =E2*Inputs!$B$5 -> 783.41779 | F11: =F2*Inputs!$B$5 -> 863.93403
A12: Change in NWC | B12: =B2*Inputs!$B$6 -> 76.406252 | C12: =C2*Inputs!$B$6 -> 84.258951 | D12: =D2*Inputs!$B$6 -> 92.918716 | E12: =E2*Inputs!$B$6 -> 102.46849 | F12: =F2*Inputs!$B$6 -> 112.99976
A13: FCFF | B13: =B10+B6-B11-B12 -> 1946.2111 | C13: =C10+C6-C11-C12 -> 2146.2342 | D13: =D10+D6-D11-D12 -> 2366.8147 | E13: =E10+E6-E11-E12 -> 2610.0655 | F13: =F10+F6-F11-F12 -> 2878.3166
A15: Note: Monetary values are in ₹ Crore; percentages are shown as %.

Sheet DCF
A1: DCF Valuation (₹ Cr, except per-share value)
A3: Particulars | B3: FY2027E | C3: FY2028E | D3: FY2029E | E3: FY2030E | F3: FY2031E
A4: FCFF | B4: =Forecast!B13 -> 1946.2111 | C4: =Forecast!C13 -> 2146.2342 | D4: =Forecast!D13 -> 2366.8147 | E4: =Forecast!E13 -> 2610.0655 | F4: =Forecast!F13 -> 2878.3166
A5: Discount Factor | B5: =1/(1+$B$8)^B11 -> 0.91117359 | C5: =1/(1+$B$8)^C11 -> 0.8302373 | D5: =1/(1+$B$8)^D11 -> 0.7564903 | E5: =1/(1+$B$8)^E11 -> 0.68929398 | F5: =1/(1+$B$8)^F11 -> 0.62806647
A6: Present Value of FCFF | B6: =B4*B5 -> 1773.3362 | C6: =C4*C5 -> 1781.8837 | D6: =D4*D5 -> 1790.4724 | E6: =E4*E5 -> 1799.1024 | F6: =F4*F5 -> 1807.7741
A8: WACC | B8: =Inputs!B7 -> 0.09748572
A9: Terminal Growth | B9: =Inputs!B8 -> 0.05
A11: Year | B11: 1 | C11: 2 | D11: 3 | E11: 4 | F11: 5
A12: PV of Forecast FCFF | B12: =SUM(B6:F6) -> 8952.5688
A14: Terminal Value | B14: =F4*(1+$B$9)/($B$8-$B$9) -> 63645.079
A15: PV of Terminal Value | B15: =B14*F5 -> 39973.34
A16: Enterprise Value | B16: =B12+B15 -> 48925.909
A17: Net Debt | B17: =Inputs!B19-Inputs!B21 -> 118.31
A18: Equity Value | B18: =B16-B17 -> 48807.599
A19: Shares Outstanding (Cr) | B19: =Inputs!B22 -> 101.7766
A20: Intrinsic Value / Share (₹) | B20: =B18/B19 -> 479.55619
A22: Current Market Price (₹) | B22: 1517.2
A23: Upside / (Downside) % | B23: =(B20/B22)-1 -> -0.68392025
A24: Valuation Date | B24: =DATE(2026,9,25) -> 46290
A27: Sensitivity Analysis — Intrinsic Value / Share (₹)
A28: WACC \ Terminal Growth | B28: 0.04 | C28: 0.045 | D28: =$B$9 -> 0.05 | E28: 0.055 | F28: 0.06
A29: 0.0875 | B29: {=(SUMPRODUCT($B$4:$F$4/(1+$A29)^$B$11:$F$11)+($F$4*(1+B$28)/( $A29-B$28))/(1+$A29)^$F$11-$B$17)/$B$19} -> 496.3454 | C29: {=(SUMPRODUCT($B$4:$F$4/(1+$A29)^$B$11:$F$11)+($F$4*(1+C$28)/( $A29-C$28))/(1+$A29)^$F$11-$B$17)/$B$19} -> 546.42502 | D29: {=(SUMPRODUCT($B$4:$F$4/(1+$A29)^$B$11:$F$11)+($F$4*(1+D$28)/( $A29-D$28))/(1+$A29)^$F$11-$B$17)/$B$19} -> 609.8592 | E29: {=(SUMPRODUCT($B$4:$F$4/(1+$A29)^$B$11:$F$11)+($F$4*(1+E$28)/( $A29-E$28))/(1+$A29)^$F$11-$B$17)/$B$19} -> 692.8116 | F29: {=(SUMPRODUCT($B$4:$F$4/(1+$A29)^$B$11:$F$11)+($F$4*(1+F$28)/( $A29-F$28))/(1+$A29)^$F$11-$B$17)/$B$19} -> 805.9285
A30: 0.0925 | B30: {=(SUMPRODUCT($B$4:$F$4/(1+$A30)^$B$11:$F$11)+($F$4*(1+B$28)/( $A30-B$28))/(1+$A30)^$F$11-$B$17)/$B$19} -> 447.97867 | C30: {=(SUMPRODUCT($B$4:$F$4/(1+$A30)^$B$11:$F$11)+($F$4*(1+C$28)/( $A30-C$28))/(1+$A30)^$F$11-$B$17)/$B$19} -> 487.78223 | D30: {=(SUMPRODUCT($B$4:$F$4/(1+$A30)^$B$11:$F$11)+($F$4*(1+D$28)/( $A30-D$28))/(1+$A30)^$F$11-$B$17)/$B$19} -> 536.95133 | E30: {=(SUMPRODUCT($B$4:$F$4/(1+$A30)^$B$11:$F$11)+($F$4*(1+E$28)/( $A30-E$28))/(1+$A30)^$F$11-$B$17)/$B$19} -> 599.2322 | F30: {=(SUMPRODUCT($B$4:$F$4/(1+$A30)^$B$11:$F$11)+($F$4*(1+F$28)/( $A30-F$28))/(1+$A30)^$F$11-$B$17)/$B$19} -> 680.67641
A31: =$B$8 -> 0.09748572 | B31: {=(SUMPRODUCT($B$4:$F$4/(1+$A31)^$B$11:$F$11)+($F$4*(1+B$28)/( $A31-B$28))/(1+$A31)^$F$11-$B$17)/$B$19} -> 408.14404 | C31: {=(SUMPRODUCT($B$4:$F$4/(1+$A31)^$B$11:$F$11)+($F$4*(1+C$28)/( $A31-C$28))/(1+$A31)^$F$11-$B$17)/$B$19} -> 440.44861 | D31: {=(SUMPRODUCT($B$4:$F$4/(1+$A31)^$B$11:$F$11)+($F$4*(1+D$28)/( $A31-D$28))/(1+$A31)^$F$11-$B$17)/$B$19} -> 479.55619 | E31: {=(SUMPRODUCT($B$4:$F$4/(1+$A31)^$B$11:$F$11)+($F$4*(1+E$28)/( $A31-E$28))/(1+$A31)^$F$11-$B$17)/$B$19} -> 527.86864 | F31: {=(SUMPRODUCT($B$4:$F$4/(1+$A31)^$B$11:$F$11)+($F$4*(1+F$28)/( $A31-F$28))/(1+$A31)^$F$11-$B$17)/$B$19} -> 589.06933
A32: 0.1025 | B32: {=(SUMPRODUCT($B$4:$F$4/(1+$A32)^$B$11:$F$11)+($F$4*(1+B$28)/( $A32-B$28))/(1+$A32)^$F$11-$B$17)/$B$19} -> 374.50602 | C32: {=(SUMPRODUCT($B$4:$F$4/(1+$A32)^$B$11:$F$11)+($F$4*(1+C$28)/( $A32-C$28))/(1+$A32)^$F$11-$B$17)/$B$19} -> 401.13768 | D32: {=(SUMPRODUCT($B$4:$F$4/(1+$A32)^$B$11:$F$11)+($F$4*(1+D$28)/( $A32-D$28))/(1+$A32)^$F$11-$B$17)/$B$19} -> 432.84205 | E32: {=(SUMPRODUCT($B$4:$F$4/(1+$A32)^$B$11:$F$11)+($F$4*(1+E$28)/( $A32-E$28))/(1+$A32)^$F$11-$B$17)/$B$19} -> 471.22102 | F32: {=(SUMPRODUCT($B$4:$F$4/(1+$A32)^$B$11:$F$11)+($F$4*(1+F$28)/( $A32-F$28))/(1+$A32)^$F$11-$B$17)/$B$19} -> 518.63034
A33: 0.1075 | B33: {=(SUMPRODUCT($B$4:$F$4/(1+$A33)^$B$11:$F$11)+($F$4*(1+B$28)/( $A33-B$28))/(1+$A33)^$F$11-$B$17)/$B$19} -> 345.9534 | C33: {=(SUMPRODUCT($B$4:$F$4/(1+$A33)^$B$11:$F$11)+($F$4*(1+C$28)/( $A33-C$28))/(1+$A33)^$F$11-$B$17)/$B$19} -> 368.23271 | D33: {=(SUMPRODUCT($B$4:$F$4/(1+$A33)^$B$11:$F$11)+($F$4*(1+D$28)/( $A33-D$28))/(1+$A33)^$F$11-$B$17)/$B$19} -> 394.3867 | E33: {=(SUMPRODUCT($B$4:$F$4/(1+$A33)^$B$11:$F$11)+($F$4*(1+E$28)/( $A33-E$28))/(1+$A33)^$F$11-$B$17)/$B$19} -> 425.52239 | F33: {=(SUMPRODUCT($B$4:$F$4/(1+$A33)^$B$11:$F$11)+($F$4*(1+F$28)/( $A33-F$28))/(1+$A33)^$F$11-$B$17)/$B$19} -> 463.21296

Sheet Comps
A1: Comparable Company Valuation (₹ Cr, except per-share data & multiples)
A3: Company | B3: P/E | C3: EV/EBITDA | D3: Market Cap (₹ Cr) | E3: Enterprise Value (₹ Cr) | F3: Data Date
A4: Jyoti Resins | B4: 12.07 | C4: 7.51 | D4: 844.44 | E4: 638.35 | F4: 46269
A5: Nikhil Adhesives | B5: 23.77 | C5: 12 | D5: 400.73 | E5: 444.6 | F5: 46269
A6: HP Adhesives | B6: 24.37 | C6: 14.49 | D6: 442.27 | E6: 370.07 | F6: 46269
A7: Hindustan Adhesive | B7: 11.19 | C7: 7.01 | D7: 171.98 | E7: 239.88 | F7: 46269
A9: Peer Median | B9: =MEDIAN(B4:B7) -> 17.92 | C9: =MEDIAN(C4:C7) -> 9.755
A11: Pidilite Implied Valuation
A12: Method | B12: Implied Equity Value (₹ Cr) | C12: Implied Value / Share (₹)
A13: P/E Method | B13: =Historicals!F11*$B$9 -> 43884.646 | C13: =B13/Inputs!$B$22 -> 431.18601
A14: EV/EBITDA Method | B14: =Historicals!F4*$C$9-Inputs!$B$19+Inputs!$B$21 -> 34231.971 | C14: =B14/Inputs!$B$22 -> 336.34422

Sheet Output
A1: Valuation Summary (₹ Cr, except per-share data)
A3: Valuation Method | B3: Implied Value / Share (₹) | E3: Valuation Method | F3: Low (₹) | G3: High (₹) | H3: Range (₹)
A4: DCF | B4: =DCF!B20 -> 479.55619 | E4: DCF Sensitivity | F4: =MIN(DCF!B29:F33) -> 345.9534 | G4: =MAX(DCF!B29:F33) -> 805.9285 | H4: =G4-F4 -> 459.9751
A5: DCF Sensitivity — Low | B5: =MIN(DCF!B29:F33) -> 345.9534 | E5: DCF Base Case | F5: =DCF!B20 -> 479.55619 | G5: =DCF!B20 -> 479.55619 | H5: =G5-F5 -> 0
A6: DCF Sensitivity — High | B6: =MAX(DCF!B29:F33) -> 805.9285 | E6: P/E Comps | F6: =Comps!C13 -> 431.18601 | G6: =Comps!C13 -> 431.18601 | H6: =G6-F6 -> 0
A7: P/E Comps | B7: =Comps!C13 -> 431.18601 | E7: EV/EBITDA Comps | F7: =Comps!C14 -> 336.34422 | G7: =Comps!C14 -> 336.34422 | H7: =G7-F7 -> 0
A8: EV/EBITDA Comps | B8: =Comps!C14 -> 336.34422 | E8: Current Market Price | F8: =DCF!B22 -> 1517.2 | G8: =DCF!B22 -> 1517.2 | H8: =G8-F8 -> 0
A9: Current Market Price | B9: =DCF!B22 -> 1517.2
A11: Key Assumption | B11: Value
A12: WACC | B12: =Inputs!B7 -> 0.09748572
A13: Terminal Growth | B13: =Inputs!B8 -> 0.05
A14: Revenue Growth | B14: =Inputs!B2 -> 0.10277561
A15: EBITDA Margin | B15: =Inputs!B3 -> 0.20889009
A16: Tax Rate | B16: =Inputs!B4 -> 0.25662
A17: Capex % of Revenue | B17: =Inputs!B5 -> 0.03628
A19: DCF Valuation Detail | B19: Value
A20: Enterprise Value (₹ Cr) | B20: =DCF!B16 -> 48925.909
A21: Net Debt (₹ Cr) | B21: =DCF!B17 -> 118.31
A22: Equity Value (₹ Cr) | B22: =DCF!B18 -> 48807.599
A23: Shares Outstanding (Cr) | B23: =DCF!B19 -> 101.7766
A24: Intrinsic Value / Share (₹) | B24: =DCF!B20 -> 479.55619
A25: Valuation Date | B25: =DCF!B24 -> 46290
A27: Comparable Valuation | B27: Median Multiple | C27: Implied Value / Share (₹)
A28: P/E | B28: =Comps!B9 -> 17.92 | C28: =Comps!C13 -> 431.18601
A29: EV/EBITDA | B29: =Comps!C9 -> 9.755 | C29: =Comps!C14 -> 336.34422
